get_unicode_home.py
get_unicode_home-0.1.0a0.dist-info/licenses/LICENSE
get_unicode_home-0.1.0a0.dist-info/METADATA
get_unicode_home-0.1.0a0.dist-info/WHEEL
get_unicode_home-0.1.0a0.dist-info/top_level.txt
get_unicode_home-0.1.0a0.dist-info/RECORD
