Metadata-Version: 2.4
Name: get-unicode-home
Version: 0.1.0a0
Summary: A cross-platform utility to get the current HOME as a Unicode string.
Author-email: Jifeng Wu <jifengwu2k@gmail.com>
License-Expression: MIT
Project-URL: Homepage, https://github.com/jifengwu2k/get-unicode-home
Project-URL: Bug Tracker, https://github.com/jifengwu2k/get-unicode-home/issues
Classifier: Programming Language :: Python :: 2
Classifier: Programming Language :: Python :: 3
Classifier: Operating System :: OS Independent
Requires-Python: >=2
License-File: LICENSE
Requires-Dist: posix-or-nt
Requires-Dist: read-unicode-environment-variables-dictionary
Requires-Dist: typing; python_version < "3.5"
Dynamic: license-file
